<?xml-model uri="http://xtriples.spatialhumanities.de/xtriples.rng" type="application/xml" schematypens="http://relaxng.org/ns/structure/1.0"?><!-- Example 14: Using the $resource variable in statement patterns --><xtriples><configuration><vocabularies><vocabulary prefix="gods" uri="http://xtriples.spatialhumanities.de/examples/gods/"/><vocabulary prefix="rdf" uri="http://www.w3.org/1999/02/22-rdf-syntax-ns#"/><vocabulary prefix="rdfs" uri="http://www.w3.org/2000/01/rdf-schema#"/><vocabulary prefix="foaf" uri="http://xmlns.com/foaf/0.1/"/><vocabulary prefix="rel" uri="http://purl.org/vocab/relationship/"/></vocabularies><triples><statement><condition>/@id=2</condition><subject prefix="gods" type="uri">/../god[@id=2 or @id=3 or @id=6 or @id=8]/@id</subject><predicate prefix="rdfs">label</predicate><object type="literal" lang="en">snakes</object></statement></triples></configuration><collection uri="http://xtriples.spatialhumanities.de/examples/gods/all.xml"><resource uri="{//god}"/></collection></xtriples>